setup.py
trhgvinh_distributions/__init__.py
trhgvinh_distributions/python_code.py
trhgvinh_distributions.egg-info/PKG-INFO
trhgvinh_distributions.egg-info/SOURCES.txt
trhgvinh_distributions.egg-info/dependency_links.txt
trhgvinh_distributions.egg-info/not-zip-safe
trhgvinh_distributions.egg-info/top_level.txt